[
  {
    "id": 1,
    "name": "Rahim Uddin",
    "description": "Hardworking and regular student",
    "tag": "science",
    "gunaboli": ["honest", "punctual", "team player"],
    "roll": 101,
    "img": "https://i.pravatar.cc/150?img=1",
    "registrationNumber": "REG2026001",
    "address": "Dhaka, Bangladesh",
    "presentCount": 45,
    "shift": "1st"
  },
  {
    "id": 2,
    "name": "Karim Hasan",
    "description": "Good in math and problem solving",
    "tag": "commerce",
    "gunaboli": ["smart", "focused", "disciplined"],
    "roll": 102,
    "img": "https://i.pravatar.cc/150?img=2",
    "registrationNumber": "REG2026002",
    "address": "Chattogram, Bangladesh",
    "presentCount": 40,
    "shift": "2nd"
  },
  {
    "id": 3,
    "name": "Ayesha Akter",
    "description": "Creative and active student",
    "tag": "arts",
    "gunaboli": ["creative", "friendly", "active"],
    "roll": 103,
    "img": "https://i.pravatar.cc/150?img=3",
    "registrationNumber": "REG2026003",
    "address": "Cumilla, Bangladesh",
    "presentCount": 48,
    "shift": "1st"
  },
  {
    "id": 4,
    "name": "Sabbir Hossain",
    "description": "Regular and responsible",
    "tag": "science",
    "gunaboli": ["responsible", "calm", "helpful"],
    "roll": 104,
    "img": "https://i.pravatar.cc/150?img=4",
    "registrationNumber": "REG2026004",
    "address": "Sylhet, Bangladesh",
    "presentCount": 42,
    "shift": "2nd"
  },
  {
    "id": 5,
    "name": "Nusrat Jahan",
    "description": "Very punctual and organized",
    "tag": "arts",
    "gunaboli": ["organized", "punctual", "neat"],
    "roll": 105,
    "img": "https://i.pravatar.cc/150?img=5",
    "registrationNumber": "REG2026005",
    "address": "Rajshahi, Bangladesh",
    "presentCount": 47,
    "shift": "1st"
  },
  {
    "id": 6,
    "name": "Tanvir Ahmed",
    "description": "Tech enthusiast student",
    "tag": "science",
    "gunaboli": ["curious", "innovative", "quick learner"],
    "roll": 106,
    "img": "https://i.pravatar.cc/150?img=6",
    "registrationNumber": "REG2026006",
    "address": "Khulna, Bangladesh",
    "presentCount": 39,
    "shift": "2nd"
  },
  {
    "id": 7,
    "name": "Mim Akter",
    "description": "Friendly and helpful",
    "tag": "arts",
    "gunaboli": ["kind", "supportive", "polite"],
    "roll": 107,
    "img": "https://i.pravatar.cc/150?img=7",
    "registrationNumber": "REG2026007",
    "address": "Barisal, Bangladesh",
    "presentCount": 44,
    "shift": "1st"
  },
  {
    "id": 8,
    "name": "Rakib Islam",
    "description": "Strong in leadership",
    "tag": "commerce",
    "gunaboli": ["leader", "confident", "bold"],
    "roll": 108,
    "img": "https://i.pravatar.cc/150?img=8",
    "registrationNumber": "REG2026008",
    "address": "Dhaka, Bangladesh",
    "presentCount": 41,
    "shift": "2nd"
  },
  {
    "id": 9,
    "name": "Farhana Yasmin",
    "description": "Very active in class",
    "tag": "science",
    "gunaboli": ["active", "energetic", "attentive"],
    "roll": 109,
    "img": "https://i.pravatar.cc/150?img=9",
    "registrationNumber": "REG2026009",
    "address": "Noakhali, Bangladesh",
    "presentCount": 49,
    "shift": "1st"
  },
  {
    "id": 10,
    "name": "Jahidul Islam",
    "description": "Regular and sincere",
    "tag": "commerce",
    "gunaboli": ["sincere", "dedicated", "calm"],
    "roll": 110,
    "img": "https://i.pravatar.cc/150?img=10",
    "registrationNumber": "REG2026010",
    "address": "Rangpur, Bangladesh",
    "presentCount": 43,
    "shift": "2nd"
  },
  {
    "id": 11,
    "name": "Sadia Islam",
    "description": "Focused and disciplined",
    "tag": "science",
    "gunaboli": ["focused", "smart", "punctual"],
    "roll": 111,
    "img": "https://i.pravatar.cc/150?img=11",
    "registrationNumber": "REG2026011",
    "address": "Dhaka, Bangladesh",
    "presentCount": 46,
    "shift": "1st"
  },
  {
    "id": 12,
    "name": "Hasan Mahmud",
    "description": "Good in teamwork",
    "tag": "commerce",
    "gunaboli": ["team player", "friendly", "helpful"],
    "roll": 112,
    "img": "https://i.pravatar.cc/150?img=12",
    "registrationNumber": "REG2026012",
    "address": "Chattogram, Bangladesh",
    "presentCount": 38,
    "shift": "2nd"
  },
  {
    "id": 13,
    "name": "Ritu Akter",
    "description": "Creative mindset",
    "tag": "arts",
    "gunaboli": ["creative", "imaginative", "kind"],
    "roll": 113,
    "img": "https://i.pravatar.cc/150?img=13",
    "registrationNumber": "REG2026013",
    "address": "Sylhet, Bangladesh",
    "presentCount": 47,
    "shift": "1st"
  },
  {
    "id": 14,
    "name": "Imran Hossain",
    "description": "Active and energetic",
    "tag": "science",
    "gunaboli": ["active", "fast learner", "confident"],
    "roll": 114,
    "img": "https://i.pravatar.cc/150?img=14",
    "registrationNumber": "REG2026014",
    "address": "Rajshahi, Bangladesh",
    "presentCount": 42,
    "shift": "2nd"
  },
  {
    "id": 15,
    "name": "Tania Sultana",
    "description": "Very responsible",
    "tag": "arts",
    "gunaboli": ["responsible", "honest", "calm"],
    "roll": 115,
    "img": "https://i.pravatar.cc/150?img=15",
    "registrationNumber": "REG2026015",
    "address": "Khulna, Bangladesh",
    "presentCount": 45,
    "shift": "1st"
  },
  {
    "id": 16,
    "name": "Rashed Khan",
    "description": "Hardworking student",
    "tag": "commerce",
    "gunaboli": ["hardworking", "disciplined", "focused"],
    "roll": 116,
    "img": "https://i.pravatar.cc/150?img=16",
    "registrationNumber": "REG2026016",
    "address": "Barisal, Bangladesh",
    "presentCount": 39,
    "shift": "2nd"
  },
  {
    "id": 17,
    "name": "Mahi Akter",
    "description": "Friendly and active",
    "tag": "arts",
    "gunaboli": ["friendly", "active", "helpful"],
    "roll": 117,
    "img": "https://i.pravatar.cc/150?img=17",
    "registrationNumber": "REG2026017",
    "address": "Cumilla, Bangladesh",
    "presentCount": 48,
    "shift": "1st"
  },
  {
    "id": 18,
    "name": "Arif Hossain",
    "description": "Good problem solver",
    "tag": "science",
    "gunaboli": ["analytical", "smart", "calm"],
    "roll": 118,
    "img": "https://i.pravatar.cc/150?img=18",
    "registrationNumber": "REG2026018",
    "address": "Noakhali, Bangladesh",
    "presentCount": 41,
    "shift": "2nd"
  },
  {
    "id": 19,
    "name": "Nadia Rahman",
    "description": "Very punctual",
    "tag": "arts",
    "gunaboli": ["punctual", "neat", "organized"],
    "roll": 119,
    "img": "https://i.pravatar.cc/150?img=19",
    "registrationNumber": "REG2026019",
    "address": "Dhaka, Bangladesh",
    "presentCount": 47,
    "shift": "1st"
  },
  {
    "id": 20,
    "name": "Fahim Ahmed",
    "description": "Confident and bold",
    "tag": "commerce",
    "gunaboli": ["confident", "leader", "smart"],
    "roll": 120,
    "img": "https://i.pravatar.cc/150?img=20",
    "registrationNumber": "REG2026020",
    "address": "Chattogram, Bangladesh",
    "presentCount": 40,
    "shift": "2nd"
  },
  {
    "id": 21,
    "name": "Shila Akter",
    "description": "Calm and polite",
    "tag": "arts",
    "gunaboli": ["polite", "kind", "calm"],
    "roll": 121,
    "img": "https://i.pravatar.cc/150?img=21",
    "registrationNumber": "REG2026021",
    "address": "Sylhet, Bangladesh",
    "presentCount": 46,
    "shift": "1st"
  },
  {
    "id": 22,
    "name": "Nayeem Islam",
    "description": "Fast learner",
    "tag": "science",
    "gunaboli": ["fast learner", "active", "focused"],
    "roll": 122,
    "img": "https://i.pravatar.cc/150?img=22",
    "registrationNumber": "REG2026022",
    "address": "Rajshahi, Bangladesh",
    "presentCount": 42,
    "shift": "2nd"
  },
  {
    "id": 23,
    "name": "Sumaiya Jahan",
    "description": "Creative thinker",
    "tag": "arts",
    "gunaboli": ["creative", "imaginative", "smart"],
    "roll": 123,
    "img": "https://i.pravatar.cc/150?img=23",
    "registrationNumber": "REG2026023",
    "address": "Khulna, Bangladesh",
    "presentCount": 48,
    "shift": "1st"
  },
  {
    "id": 24,
    "name": "Rakibul Hasan",
    "description": "Strong leadership skills",
    "tag": "commerce",
    "gunaboli": ["leader", "confident", "bold"],
    "roll": 124,
    "img": "https://i.pravatar.cc/150?img=24",
    "registrationNumber": "REG2026024",
    "address": "Barisal, Bangladesh",
    "presentCount": 41,
    "shift": "2nd"
  },
  {
    "id": 25,
    "name": "Tasnim Akter",
    "description": "Very sincere student",
    "tag": "science",
    "gunaboli": ["sincere", "dedicated", "honest"],
    "roll": 125,
    "img": "https://i.pravatar.cc/150?img=25",
    "registrationNumber": "REG2026025",
    "address": "Cumilla, Bangladesh",
    "presentCount": 47,
    "shift": "1st"
  }
]